nbic/__init__.py
nbic/_modidx.py
nbic/base.py
nbic/skip.py
nbic-0.0.1.dist-info/LICENSE
nbic-0.0.1.dist-info/METADATA
nbic-0.0.1.dist-info/WHEEL
nbic-0.0.1.dist-info/entry_points.txt
nbic-0.0.1.dist-info/top_level.txt
nbic-0.0.1.dist-info/RECORD
