Metadata-Version: 2.1
Name: nbic
Version: 0.0.1
Summary: jupyter notebook toolkit
Home-page: https://github.com/dsm-72/nbic
Author: dsm-72
Author-email: sumner.magruder@yale.edu
License: Apache Software License 2.0
Keywords: nbdev jupyter notebook python nbic nb nbs magic mgc
Classifier: Development Status :: 4 - Beta
Classifier: Intended Audience :: Developers
Classifier: Natural Language :: English
Classifier: Programming Language :: Python :: 3.11
Classifier: License :: OSI Approved :: Apache Software License
Requires-Python: >=3.11
License-File: LICENSE
Requires-Dist: nlit
Requires-Dist: ipython
Requires-Dist: ipywidgets
Provides-Extra: dev
Requires-Dist: ipython ; extra == 'dev'
